{
  "response": {
    "daily": {
      "precipitation_sum": [
        0.5,
        2.8,
        10.1,
        32.8,
        11.7,
        3.8,
        2.0
      ],
      "rain_sum": [
        0.5,
        2.8,
        10.1,
        32.8,
        11.7,
        3.8,
        2.0
      ],
      "snowfall_sum": [
        0.0,
        0.0,
        0.0,
        0.0,
        0.0,
        0.0,
        0.0
      ],
      "temperature_2m_max": [
        9.3,
        7.4,
        5.7,
        6.4,
        6.5,
        8.7,
        7.2
      ],
      "temperature_2m_mean": [
        5.3,
        4.2,
        3.3,
        5.0,
        4.8,
        5.6,
        4.2
      ],
      "temperature_2m_min": [
        1.5,
        0.4,
        0.2,
        3.5,
        3.9,
        2.8,
        1.1
      ],
      "time": [
        "2025-07-01",
        "2025-07-02",
        "2025-07-03",
        "2025-07-04",
        "2025-07-05",
        "2025-07-06",
        "2025-07-07"
      ]
    },
    "daily_units": {
      "precipitation_sum": "mm",
      "rain_sum": "mm",
      "snowfall_sum": "cm",
      "temperature_2m_max": "\u00b0C",
      "temperature_2m_mean": "\u00b0C",
      "temperature_2m_min": "\u00b0C",
      "time": "iso8601"
    },
    "elevation": 1345.0,
    "generationtime_ms": 4.238128662109375,
    "latitude": 56.766254,
    "longitude": -4.90567,
    "timezone": "Europe/London",
    "timezone_abbreviation": "GMT+1",
    "utc_offset_seconds": 3600
  },
  "url": "https://archive-api.open-meteo.com/v1/archive?latitude=56.797&longitude=-5.003&elevation=1345&timezone=Europe%2FLondon&start_date=2025-07-01&end_date=2025-07-07&daily=temperature_2m_mean%2Ctemperature_2m_max%2Ctemperature_2m_min%2Cprecipitation_sum%2Crain_sum%2Csnowfall_sum"
}
